autograder_cli/__init__.py
autograder_cli/build_autograder.py
autograder_cli/create_upload.py
autograder_cli/run_gradescope.py
autograder_cli/run_local.py
autograder_cli/run_prairielearn.py
autograder_platform/__init__.py
autograder_platform/cli.py
autograder_platform/Executors/Environment.py
autograder_platform/Executors/Executor.py
autograder_platform/Executors/__init__.py
autograder_platform/Executors/common.py
autograder_platform/StudentSubmission/AbstractStudentSubmission.py
autograder_platform/StudentSubmission/AbstractValidator.py
autograder_platform/StudentSubmission/GenericValidators.py
autograder_platform/StudentSubmission/ISubmissionProcess.py
autograder_platform/StudentSubmission/SubmissionProcessFactory.py
autograder_platform/StudentSubmission/__init__.py
autograder_platform/StudentSubmission/common.py
autograder_platform/StudentSubmissionImpl/__init__.py
autograder_platform/StudentSubmissionImpl/Python/AbstractPythonImportFactory.py
autograder_platform/StudentSubmissionImpl/Python/PythonEnvironment.py
autograder_platform/StudentSubmissionImpl/Python/PythonFileImportFactory.py
autograder_platform/StudentSubmissionImpl/Python/PythonModuleMockImportFactory.py
autograder_platform/StudentSubmissionImpl/Python/PythonSubmission.py
autograder_platform/StudentSubmissionImpl/Python/PythonSubmissionProcess.py
autograder_platform/StudentSubmissionImpl/Python/PythonValidators.py
autograder_platform/StudentSubmissionImpl/Python/Runners.py
autograder_platform/StudentSubmissionImpl/Python/__init__.py
autograder_platform/StudentSubmissionImpl/Python/common.py
autograder_platform/Tasks/Task.py
autograder_platform/Tasks/TaskRunner.py
autograder_platform/Tasks/__init__.py
autograder_platform/Tasks/common.py
autograder_platform/TestingFramework/Assertions.py
autograder_platform/TestingFramework/SingleFunctionMock.py
autograder_platform/TestingFramework/__init__.py
autograder_platform/config/Config.py
autograder_platform/config/__init__.py
128autograder-5.2.2.dist-info/METADATA
128autograder-5.2.2.dist-info/WHEEL
128autograder-5.2.2.dist-info/entry_points.txt
128autograder-5.2.2.dist-info/top_level.txt
128autograder-5.2.2.dist-info/RECORD
