Metadata-Version: 2.4
Name: 128Autograder
Version: 5.2.2
Author: Gregory Bell
Maintainer: Gregory Bell
Requires-Python: >=3.11.0
Requires-Dist: HybridJSONTestRunner==0.8.1
Requires-Dist: dill==0.3.9
Requires-Dist: Better-PyUnit-Format==0.2.3
Requires-Dist: schema==0.7.5
Requires-Dist: requests==2.31.0
Requires-Dist: tomli==2.0.1
Provides-Extra: dev
Requires-Dist: coverage[toml]; extra == "dev"
Requires-Dist: build; extra == "dev"
